delfino_docker/__init__.py
delfino_docker/config.py
delfino_docker-5.0.0.dist-info/METADATA
delfino_docker-5.0.0.dist-info/WHEEL
delfino_docker-5.0.0.dist-info/entry_points.txt
delfino_docker-5.0.0.dist-info/licenses/LICENSE.md
delfino_docker-5.0.0.dist-info/RECORD
