Metadata-Version: 2.4
Name: delfino-docker
Version: 5.0.0
Summary: A delfino plugin with helper scripts for working with docker.
Author-email: Radek Lat <radek.lat@gmail.com>
License: MIT License
License-File: LICENSE.md
Classifier: Development Status :: 5 - Production/Stable
Classifier: Environment :: Console
Classifier: Intended Audience :: Developers
Classifier: License :: OSI Approved :: MIT License
Classifier: Operating System :: OS Independent
Classifier: Programming Language :: Python :: 3
Classifier: Programming Language :: Python :: 3 :: Only
Classifier: Programming Language :: Python :: 3.10
Classifier: Programming Language :: Python :: 3.11
Classifier: Programming Language :: Python :: 3.12
Classifier: Programming Language :: Python :: 3.13
Classifier: Topic :: Software Development
Classifier: Topic :: Utilities
Requires-Python: >=3.10.0
Requires-Dist: delfino>=5.0.1
Requires-Dist: packaging>=23.0
